PySpeedMacro/PSMInterface.py
PySpeedMacro/PSMMain.py
PySpeedMacro/PSMMouse.py
PySpeedMacro/__init__.py
PySpeedMacro-0.0.0.16.dist-info/LICENSE
PySpeedMacro-0.0.0.16.dist-info/METADATA
PySpeedMacro-0.0.0.16.dist-info/WHEEL
PySpeedMacro-0.0.0.16.dist-info/top_level.txt
PySpeedMacro-0.0.0.16.dist-info/RECORD
