Metadata-Version: 2.1
Name: PySpeedMacro
Version: 0.0.0.16
Summary: A fast and easy library for scripting and macroing
Home-page: https://github.com/BaneofRogue/PySpeedMacro
Author: William Keller
Author-email: author@example.com
Project-URL: Bug Tracker, https://github.com/BaneofRogue/PySpeedMacro/issues
Classifier: Programming Language :: Python :: 3
Classifier: License :: OSI Approved :: MIT License
Classifier: Operating System :: OS Independent
License-File: LICENSE
